threatintel/cli.py
threatintel/server.py
threatintel/settings.py
threatintel/threatintel.py
threatintel/tools.py
threatintel/visualizations.py
mseep_fastmcp_threatintel-0.2.9.dist-info/METADATA
mseep_fastmcp_threatintel-0.2.9.dist-info/WHEEL
mseep_fastmcp_threatintel-0.2.9.dist-info/entry_points.txt
mseep_fastmcp_threatintel-0.2.9.dist-info/RECORD
